{
  "GUID": "59c9a1",
  "Name": "Custom_Token",
  "Transform": {
    "posX": 22.2120476,
    "posY": -0.892419755,
    "posZ": -19.5687256,
    "rotX": -2.22535235e-9,
    "rotY": 179.992569,
    "rotZ": 1.04832032e-9,
    "scaleX": 3.31176257,
    "scaleY": 1,
    "scaleZ": 3.31176257
  },
  "Nickname": "Character Sheet Template",
  "Description": "See the script on this object for further directions.",
  "GMNotes": "",
  "AltLookAngle": {
    "x": 0,
    "y": 0,
    "z": 0
  },
  "ColorDiffuse": {
    "r": 1,
    "g": 1,
    "b": 1
  },
  "LayoutGroupSortIndex": 0,
  "Value": 0,
  "Locked": true,
  "Grid": true,
  "Snap": true,
  "IgnoreFoW": false,
  "MeasureMovement": false,
  "DragSelectable": true,
  "Autoraise": true,
  "Sticky": true,
  "Tooltip": true,
  "GridProjection": false,
  "HideWhenFaceDown": false,
  "Hands": false,
  "CustomImage": {
    "ImageURL": "https://steamusercontent-a.akamaihd.net/ugc/794235468864125925/C540F82E25949E315CF95E344F762D3AC0D6E36B/",
    "ImageSecondaryURL": "",
    "ImageScalar": 1,
    "WidthScale": 0,
    "CustomToken": {
      "Thickness": 0.2,
      "MergeDistancePixels": 15,
      "StandUp": false,
      "Stackable": false
    }
  },
  "LuaScript": "--[[    Character Sheet Template    by: MrStump\r\n\r\nYou can set up your own character sheet if you follow these steps.\r\n\r\nStep 1) Change the character sheet image\r\n    -Right click on the character sheet, click Custom\r\n    -Replace the image URL with one for your character sheet\r\n    -Click import, make sure your sheet loads\r\n    -SAVE THE GAME (the table setup)\r\n    -LOAD FROM THAT SAVE YOU JUST MADE\r\n\r\nStep 2) Edit script to fit your character sheet\r\n    -Below you will see some general options, and then the big data table\r\n    -The data table is what determines how many of which buttons are made\r\n        -Checkboxes\r\n        -Counters\r\n        -Textboxes\r\n    -By default, there are 3 of each. You can add more or remove entries\r\n    -If you intend to add/remove, be sure only to add/remove ENTRIES\r\n        -This is what an entry looks like:\r\n            {\r\n                pos   = {-0.977,0.1,-0.589},\r\n                size  = 800,\r\n                state = false\r\n            },\r\n        -Deleting the whole thing would remove that specific item on the sheet\r\n        -Copy and pasting it after another entry would create another\r\n    -Each entry type has unique data points (pos, size, state, etc)\r\n        -Do not try to add in your own data points or remove them individually\r\n        -There is a summary of what each point does at the top of its category\r\n\r\nStep 3) Save and check script changes\r\n    -Hit Save & Apply in the script window to save your code\r\n    -You can edit your code as needed and Save+Apply as often as needed\r\n    -When you are finished, make disableSave = false below then Save+apply\r\n        -This enables saving, so your sheet will remember whats on it.\r\n\r\nBonus) Finding/Editing Positions for elements\r\n    I have included a tool to get positions for buttons in {x,y,z} form\r\n    Place it where you want the center of your element to be\r\n    Then copy the table from the notes (lower right of screen)\r\n        You can highlight it and CTRL+C\r\n    Paste it into the data table where needed (pos=)\r\n    If you want to manually tweek the values:\r\n        {0,0,0} is the center of the character sheet\r\n        {1,0,0} is right, {-1,0,0} is left\r\n        {0,0,-1} is up, {0,0,1} is down\r\n        0.1 for Y is the height off of the page.\r\n            If it was 0, it would be down inside the model of the sheet\r\n\r\nBegin editing below:    ]]\r\n\n--Set this to true if you do not want Blood Potency related values to\n--update automatically (if you are using homebrew or custom values for example)\ndisablePotencyUpdate = false\n\r\n--Set this to true while editing and false when you have finished\r\ndisableSave = false\r\n--Remember to set this to false once you are done making changes\r\n--Then, after you save & apply it, save your game too\r\n\r\n--Color information for button text (r,g,b, values of 0-1)\r\nbuttonFontColor = {0,0,0}\r\n--Color information for button background\r\nbuttonColor = {1,1,1}\r\n--Change scale of button (Avoid changing if possible)\r\nbuttonScale = {0.1,0.1,0.1}\r\n\r\n--This is the button placement information\r\ndefaultButtonData = {\r\n    --Add checkboxes\r\n    checkbox = {\r\n        --[[\r\n        pos   = the position (pasted from the helper tool)\r\n        size  = height/width/font_size for checkbox\r\n        state = default starting value for checkbox (true=checked, false=not)\r\n        ]]\n\r\n        --Advantages & Flaws\r\n        {pos   = {-0.288,0.1,-0.7}, size  = 160, state = false, tag = \"adv1\"},\r\n        {pos   = {-0.2345,0.1,-0.7}, size  = 160, state = false, tag = \"adv1\"},\r\n        {pos   = {-0.181,0.1,-0.7}, size  = 160, state = false, tag = \"adv1\"},\n        {pos   = {-0.1275,0.1,-0.7}, size  = 160, state = false, tag = \"adv1\"},\n        {pos   = {-0.074,0.1,-0.7}, size  = 160, state = false, tag = \"adv1\"},\n\r\n        {pos   = {-0.288,0.1,-0.5782}, size  = 160, state = false, tag = \"adv2\"},\r\n        {pos   = {-0.2345,0.1,-0.5782}, size  = 160, state = false, tag = \"adv2\"},\r\n        {pos   = {-0.181,0.1,-0.5782}, size  = 160, state = false, tag = \"adv2\"},\n        {pos   = {-0.1275,0.1,-0.5782}, size  = 160, state = false, tag = \"adv2\"},\n        {pos   = {-0.074,0.1,-0.5782}, size  = 160, state = false, tag = \"adv2\"},\n\r\n        {pos   = {-0.288,0.1,-0.4564}, size  = 160, state = false, tag = \"adv3\"},\r\n        {pos   = {-0.2345,0.1,-0.4564}, size  = 160, state = false, tag = \"adv3\"},\r\n        {pos   = {-0.181,0.1,-0.4564}, size  = 160, state = false, tag = \"adv3\"},\n        {pos   = {-0.1275,0.1,-0.4564}, size  = 160, state = false, tag = \"adv3\"},\n        {pos   = {-0.074,0.1,-0.4564}, size  = 160, state = false, tag = \"adv3\"},\n\r\n        {pos   = {-0.288,0.1,-0.3346}, size  = 160, state = false, tag = \"adv4\"},\r\n        {pos   = {-0.2345,0.1,-0.3346}, size  = 160, state = false, tag = \"adv4\"},\r\n        {pos   = {-0.181,0.1,-0.3346}, size  = 160, state = false, tag = \"adv4\"},\n        {pos   = {-0.1275,0.1,-0.3346}, size  = 160, state = false, tag = \"adv4\"},\n        {pos   = {-0.074,0.1,-0.3346}, size  = 160, state = false, tag = \"adv4\"},\n\r\n        {pos   = {-0.288,0.1,-0.2128}, size  = 160, state = false, tag = \"adv5\"},\r\n        {pos   = {-0.2345,0.1,-0.2128}, size  = 160, state = false, tag = \"adv5\"},\r\n        {pos   = {-0.181,0.1,-0.2128}, size  = 160, state = false, tag = \"adv5\"},\n        {pos   = {-0.1275,0.1,-0.2128}, size  = 160, state = false, tag = \"adv5\"},\n        {pos   = {-0.074,0.1,-0.2128}, size  = 160, state = false, tag = \"adv5\"},\n\r\n        {pos   = {-0.288,0.1,-0.091}, size  = 160, state = false, tag = \"adv6\"},\r\n        {pos   = {-0.2345,0.1,-0.091}, size  = 160, state = false, tag = \"adv6\"},\r\n        {pos   = {-0.181,0.1,-0.091}, size  = 160, state = false, tag = \"adv6\"},\n        {pos   = {-0.1275,0.1,-0.091}, size  = 160, state = false, tag = \"adv6\"},\n        {pos   = {-0.074,0.1,-0.091}, size  = 160, state = false, tag = \"adv6\"},\n\r\n        {pos   = {-0.288,0.1,0.0308}, size  = 160, state = false, tag = \"adv7\"},\r\n        {pos   = {-0.2345,0.1,0.0308}, size  = 160, state = false, tag = \"adv7\"},\r\n        {pos   = {-0.181,0.1,0.0308}, size  = 160, state = false, tag = \"adv7\"},\n        {pos   = {-0.1275,0.1,0.0308}, size  = 160, state = false, tag = \"adv7\"},\n        {pos   = {-0.074,0.1,0.0308}, size  = 160, state = false, tag = \"adv7\"},\n\r\n        {pos   = {-0.288,0.1,0.1526}, size  = 160, state = false, tag = \"adv8\"},\r\n        {pos   = {-0.2345,0.1,0.1526}, size  = 160, state = false, tag = \"adv8\"},\r\n        {pos   = {-0.181,0.1,0.1526}, size  = 160, state = false, tag = \"adv8\"},\n        {pos   = {-0.1275,0.1,0.1526}, size  = 160, state = false, tag = \"adv8\"},\n        {pos   = {-0.074,0.1,0.1526}, size  = 160, state = false, tag = \"adv8\"},\n\r\n        {pos   = {-0.288,0.1,0.2744}, size  = 160, state = false, tag = \"adv9\"},\r\n        {pos   = {-0.2345,0.1,0.2744}, size  = 160, state = false, tag = \"adv9\"},\r\n        {pos   = {-0.181,0.1,0.2744}, size  = 160, state = false, tag = \"adv9\"},\n        {pos   = {-0.1275,0.1,0.2744}, size  = 160, state = false, tag = \"adv9\"},\n        {pos   = {-0.074,0.1,0.2744}, size  = 160, state = false, tag = \"adv9\"},\n\r\n        {pos   = {-0.288,0.1,0.3962}, size  = 160, state = false, tag = \"adv10\"},\r\n        {pos   = {-0.2345,0.1,0.3962}, size  = 160, state = false, tag = \"adv10\"},\r\n        {pos   = {-0.181,0.1,0.3962}, size  = 160, state = false, tag = \"adv10\"},\n        {pos   = {-0.1275,0.1,0.3962}, size  = 160, state = false, tag = \"adv10\"},\n        {pos   = {-0.074,0.1,0.3962}, size  = 160, state = false, tag = \"adv10\"},\n\r\n        {pos   = {-0.288,0.1,0.518}, size  = 160, state = false, tag = \"adv11\"},\r\n        {pos   = {-0.2345,0.1,0.518}, size  = 160, state = false, tag = \"adv11\"},\r\n        {pos   = {-0.181,0.1,0.518}, size  = 160, state = false, tag = \"adv11\"},\n        {pos   = {-0.1275,0.1,0.518}, size  = 160, state = false, tag = \"adv11\"},\n        {pos   = {-0.074,0.1,0.518}, size  = 160, state = false, tag = \"adv11\"},\n\n\n        --Blood Potency\r\n        {pos   = {0.642,0.1,-0.81}, size  = 160, state = false, tag = \"potency\"},\r\n        {pos   = {0.6955,0.1,-0.81}, size  = 160, state = false, tag = \"potency\"},\r\n        {pos   = {0.749,0.1,-0.81}, size  = 160, state = false, tag = \"potency\"},\n        {pos   = {0.8025,0.1,-0.81}, size  = 160, state = false, tag = \"potency\"},\n        {pos   = {0.856,0.1,-0.81}, size  = 160, state = false, tag = \"potency\"},\n\r\n        {pos   = {0.925,0.1,-0.81}, size  = 160, state = false, tag = \"potency\"},\r\n        {pos   = {0.9785,0.1,-0.81}, size  = 160, state = false, tag = \"potency\"},\r\n        {pos   = {1.032,0.1,-0.81}, size  = 160, state = false, tag = \"potency\"},\n        {pos   = {1.0855,0.1,-0.81}, size  = 160, state = false, tag = \"potency\"},\n        {pos   = {1.139,0.1,-0.81}, size  = 160, state = false, tag = \"potency\"},\n\n\n        --Play Mode\r\n        {pos   = {1.5,0.1,2}, size  = 800, state = false, tag = \"edit\"},\r\n        {pos   = {0,0,0}, size  = 0, state = false, tag = \"dummy\"},\n\n\r\n        --End of checkboxes\r\n    },\n\r\n   \r\n    --Add counters that have a + and - button\r\n    counter = {\r\n        --[[\r\n        pos    = the position (pasted from the helper tool)\r\n        size   = height/width/font_size for counter\r\n        value  = default starting value for counter\r\n        hideBG = if background of counter is hidden (true=hidden, false=not)\r\n        ]]\n\r\r\n        --End of counters\r\n    },\r\n    --Add editable text boxes\r\n    textbox = {\r\n        --[[\r\n        pos       = the position (pasted from the helper tool)\r\n        rows      = how many lines of text you want for this box\r\n        width     = how wide the text box is\r\n        font_size = size of text. This and \"rows\" effect overall height\r\n        label     = what is shown when there is no text. \"\" = nothing\r\n        value     = text entered into box. \"\" = nothing\r\n        alignment = Number to indicate how you want text aligned\r\n                    (1=Automatic, 2=Left, 3=Center, 4=Right, 5=Justified)\r\n        ]]\n        --Tenets\r\n        {   pos       = {-0.885,0.1,-1.26},\r\n            rows      = 16, width = 4000, font_size = 200,\r\n            label     = \"\", value     = \"\", alignment = 2},\n        --Touchstones\r\n        {   pos       = {0.01,0.1,-1.26},\r\n            rows      = 16, width = 4000, font_size = 200,\r\n            label     = \"\", value     = \"\", alignment = 2},\n        --Clan Bane\r\n        {   pos       = {0.9,0.1,-1.26},\r\n            rows      = 16, width = 4000, font_size = 200,\r\n            label     = \"\", value     = \"\", alignment = 2},\n\n        --Blood Surge\r\n        {   pos       = {0.36,0.1,-0.63},\r\n            rows      = 2, width = 2800, font_size = 200,\r\n            label     = \"Blood Surge\", value     = \"\", alignment = 3},\n        --Mend Amount\r\n        {   pos       = {1,0.1,-0.63},\r\n            rows      = 2, width = 2800, font_size = 200,\r\n            label     = \"Mend Amount\", value     = \"\", alignment = 3},\n        --Power Bonus\r\n        {   pos       = {0.36,0.1,-0.41},\r\n            rows      = 2, width = 2800, font_size = 200,\r\n            label     = \"Power Bonus\", value     = \"\", alignment = 3},\n        --Rouse Re-Roll\r\n        {   pos       = {1,0.1,-0.41},\r\n            rows      = 2, width = 2800, font_size = 200,\r\n            label     = \"Rouse Re-Roll\", value     = \"\", alignment = 3},\n        --Feeding Penalty\r\n        {   pos       = {0.36,0.1,-0.19},\r\n            rows      = 3, width = 2800, font_size = 200,\r\n            label     = \"Feeding Penalty\", value     = \"\", alignment = 3},\n        --Bane Severity\r\n        {   pos       = {1,0.1,-0.2},\r\n            rows      = 2, width = 2800, font_size = 200,\r\n            label     = \"Bane Severity\", value     = \"\", alignment = 3},\n\n        --Advantages & Flaws\r\n        {   pos       = {-0.8,0.1,-0.7},\r\n            rows      = 1, width = 4400, font_size = 300,\r\n            label     = \"\", value     = \"\", alignment = 2},\r\n        {   pos       = {-0.8,0.1,-0.578},\r\n            rows      = 1, width = 4400, font_size = 300,\r\n            label     = \"\", value     = \"\", alignment = 2},\r\r\n        {   pos       = {-0.8,0.1,-0.456},\r\n            rows      = 1, width = 4400, font_size = 300,\r\n            label     = \"\", value     = \"\", alignment = 2},\r\r\n        {   pos       = {-0.8,0.1,-0.334},\r\n            rows      = 1, width = 4400, font_size = 300,\r\n            label     = \"\", value     = \"\", alignment = 2},\r\r\n        {   pos       = {-0.8,0.1,-0.212},\r\n            rows      = 1, width = 4400, font_size = 300,\r\n            label     = \"\", value     = \"\", alignment = 2},\r\r\n        {   pos       = {-0.8,0.1,-0.09},\r\n            rows      = 1, width = 4400, font_size = 300,\r\n            label     = \"\", value     = \"\", alignment = 2},\r\r\n        {   pos       = {-0.8,0.1,0.032},\r\n            rows      = 1, width = 4400, font_size = 300,\r\n            label     = \"\", value     = \"\", alignment = 2},\r\r\n        {   pos       = {-0.8,0.1,0.154},\r\n            rows      = 1, width = 4400, font_size = 300,\r\n            label     = \"\", value     = \"\", alignment = 2},\r\r\n        {   pos       = {-0.8,0.1,0.276},\r\n            rows      = 1, width = 4400, font_size = 300,\r\n            label     = \"\", value     = \"\", alignment = 2},\r\r\n        {   pos       = {-0.8,0.1,0.398},\r\n            rows      = 1, width = 4400, font_size = 300,\r\n            label     = \"\", value     = \"\", alignment = 2},\r\r\n        {   pos       = {-0.8,0.1,0.52},\r\n            rows      = 1, width = 4400, font_size = 300,\r\n            label     = \"\", value     = \"\", alignment = 2},\r\n\n        --XP\r\n        {   pos       = {0.91,0.1,-0.025},\r\n            rows      = 1, width = 3400, font_size = 300,\r\n            label     = \"\", value     = \"\", alignment = 3},\r\n        {   pos       = {0.91,0.1,0.1},\r\n            rows      = 1, width = 3400, font_size = 300,\r\n            label     = \"\", value     = \"\", alignment = 3},\n\n        --Details\r\n        {   pos       = {0.8,0.1,0.27},\r\n            rows      = 1, width = 4500, font_size = 300,\r\n            label     = \"\", value     = \"\", alignment = 2},\r\n        {   pos       = {0.8,0.1,0.377},\r\n            rows      = 1, width = 4500, font_size = 300,\r\n            label     = \"\", value     = \"\", alignment = 2},\r\n        {   pos       = {0.8,0.1,0.483},\r\n            rows      = 1, width = 4500, font_size = 300,\r\n            label     = \"\", value     = \"\", alignment = 2},\r\n        {   pos       = {0.8,0.1,0.59},\r\n            rows      = 1, width = 4500, font_size = 300,\r\n            label     = \"\", value     = \"\", alignment = 2},\r\n        {   pos       = {0.67,0.1,0.78},\r\n            rows      = 2, width = 5800, font_size = 200,\r\n            label     = \"\", value     = \"\", alignment = 2},\r\n        {   pos       = {0.67,0.1,1},\r\n            rows      = 2, width = 5800, font_size = 200,\r\n            label     = \"\", value     = \"\", alignment = 2},\r\n        {   pos       = {0.67,0.1,1.48},\r\n            rows      = 16, width = 5800, font_size = 200,\r\n            label     = \"\", value     = \"\", alignment = 2},\n\n        --Notes\r\n        {   pos       = {-0.68,0.1,1.25},\r\n            rows      = 26, width = 5800, font_size = 200,\r\n            label     = \"\", value     = \"\", alignment = 2},\n\r\n        --End of textboxes\r\n    }\r\n}\r\n\r\n\r\n\r\n--Lua beyond this point, I recommend doing something more fun with your life\r\n\r\n\r\n\r\n--Save function\r\nfunction updateSave()\r\n    saved_data = JSON.encode(ref_buttonData)\r\n    if disableSave==true then saved_data=\"\" end\r\n    self.script_state = saved_data\r\nend\r\n\r\n--Startup procedure\r\nfunction onload(saved_data)\r\n    if disableSave==true then saved_data=\"\" end\r\n    if saved_data ~= \"\" then\r\n        local loaded_data = JSON.decode(saved_data)\r\n        ref_buttonData = loaded_data\r\n    else\r\n        ref_buttonData = defaultButtonData\r\n    end\r\n\r\n    spawnedButtonCount = 0\r\n    createCheckbox()\r\n    createCounter()\r\n    createTextbox()\n    updateBloodPotencyValues()\r\nend\r\n\r\n\r\n\r\n--Click functions for buttons\r\n\r\n\r\n\r\n--Checks or unchecks the given box (change colour)\r\nfunction click_checkbox(tableIndex, buttonIndex)\n\nif ref_buttonData.checkbox[tableIndex].tag == \"edit\" then\n    if ref_buttonData.checkbox[tableIndex].state == true then\r\n        ref_buttonData.checkbox[tableIndex].state = false\r\n        self.editButton({index=buttonIndex, color=\"White\"})\n    else\r\n        ref_buttonData.checkbox[tableIndex].state = true\r\n        self.editButton({index=buttonIndex, color=\"Black\"})\n    end\nelse\nfor i, data in ipairs(ref_buttonData.checkbox) do\nif data.tag == \"edit\" then\nif data.state == false then\r\n    if ref_buttonData.checkbox[tableIndex].state == true then\n        if ref_buttonData.checkbox[tableIndex+1].tag == ref_buttonData.checkbox[tableIndex].tag then\n            if ref_buttonData.checkbox[tableIndex+1].state == true then\n                for i, data in ipairs(ref_buttonData.checkbox) do\n                    if data.tag == ref_buttonData.checkbox[tableIndex].tag then\n                        if i > tableIndex then\r\n                            ref_buttonData.checkbox[i].state = false\r\n                            self.editButton({index=buttonIndex+i-tableIndex, color=\"White\"})\n                        end\n                    end\n                end\n            else\r\n                ref_buttonData.checkbox[tableIndex].state = false\r\n                self.editButton({index=buttonIndex, color=\"White\"})\n            end\n        else\r\n            ref_buttonData.checkbox[tableIndex].state = false\r\n            self.editButton({index=buttonIndex, color=\"White\"})\n        end\r\n    else\n        for i, data in ipairs(ref_buttonData.checkbox) do\n            if data.tag == ref_buttonData.checkbox[tableIndex].tag then\n                if i <= tableIndex then\r\n                    ref_buttonData.checkbox[i].state = true\r\n                    self.editButton({index=buttonIndex+i-tableIndex, color=\"Black\"})\n                end\n            end\n        end\r\r\n    end\n\n    if ref_buttonData.checkbox[tableIndex].tag == \"potency\" then\n        updateBloodPotencyValues()\n    end\nelseif data.state == true then\n        local dheight = 5\n        for i, data in ipairs(ref_buttonData.checkbox) do\n            if data.tag == ref_buttonData.checkbox[tableIndex].tag and data.state == true then\r\n                local dice = spawnObject({type = \"Custom_Dice\", position = {0,dheight,0}})\n                dice.setCustomObject({type = 3, image = \"https://steamusercontent-a.akamaihd.net/ugc/957476100395980607/FBE78762303A5315D6FB0697D051C7B49D955054/\"})\n                dice.setName(ref_buttonData.checkbox[tableIndex].tag)\n                dice.setLuaScript(\"local isRolling = false\\nhighlightDuration = 30\\n\\nfunction onUpdate()\\n    if not self.resting then \\n        self.highlightOff()\\n        isRolling = true\\n    elseif isRolling and self.resting then\\n        isRolling = false\\n        local value = self.getValue()\\n        if value == 1 then\\n            self.highlightOn({0.856, 0.1, 0.094}, highlightDuration)\\n        elseif value == 10 then\\n            self.highlightOn({0.192, 0.701, 0.168}, highlightDuration)\\n        elseif value >= 6 then \\n            self.highlightOn({1, 1, 1}, highlightDuration) \\n        else\\n            self.highlightOff()\\n        end\\n    end\\nend\")\n                dice.use_hands = true\n                dheight = dheight + 1\n            end\n        end\nend\nend\nend\nend\r\n    updateSave()\r\nend\n\n\n-- Update values dependent on Blood Potency (according to basic rules)\nfunction updateBloodPotencyValues()\n    if disablePotencyUpdate == false then\n        bp = 0\n        for i, data in ipairs(ref_buttonData.checkbox) do\n            if data.tag == \"potency\" then\n                if data.state == true then\r\n                    bp = bp + 1\n                end\n            end\n        end\n        for i, data in ipairs(self.getInputs()) do\n            if data.label == \"Blood Surge\" then\n                self.editInput({index = data.index,\n                value = \"Add \"..(math.ceil(bp / 2))..\" die\"})\n            end\n            if data.label == \"Mend Amount\" then\n                self.editInput({index = data.index,\n                value = (math.ceil(bp / 2 + 0.5) - math.floor(math.max(bp,5)/6))..\" point of\"..\n                \"\\nsuperficial damage\"})\n            end\n            if data.label == \"Power Bonus\" then\n                self.editInput({index = data.index,\n                value = \"Add \"..(math.floor(bp / 2))..\" die\"})\n            end\n            if data.label == \"Rouse Re-Roll\" then\n                self.editInput({index = data.index,\n                value = \"Level \"..(math.ceil(bp / 2))..\n                \"\\n and below\"})\n            end\n            if data.label == \"Feeding Penalty\" then\n                self.editInput({index = data.index,\n                value = \"Animal / bag blood slake \"..(math.max(0,math.min(100,(150-bp*50))))..\"%\"..\n                \"\\nSlake \"..(math.max(0,math.ceil(bp / 4 - 1.25) + math.floor(math.min(bp,4)/4)))..\" less Hunger per human\"..\n                \"\\nMust kill for Hunger below \"..(math.max(1,math.floor(bp / 3 + 0.5)))})\n            end\n            if data.label == \"Bane Severity\" then\n                self.editInput({index = data.index,\n                value = (math.ceil(bp / 2))})\n            end\n        end\n    end\nend\n\r\n\r\n--Applies value to given counter display\r\nfunction click_counter(tableIndex, buttonIndex, amount)\r\n    ref_buttonData.counter[tableIndex].value = ref_buttonData.counter[tableIndex].value + amount\r\n    self.editButton({index=buttonIndex, label=ref_buttonData.counter[tableIndex].value})\r\n    updateSave()\r\nend\r\n\r\n--Updates saved value for given text box\r\nfunction click_textbox(i, value, selected)\r\n    if selected == false then\r\n        ref_buttonData.textbox[i].value = value\r\n        updateSave()\r\n    end\r\nend\r\n\r\n--Dud function for if you have a background on a counter\r\nfunction click_none() end\r\n\r\n\r\n\r\n--Button creation\r\n\r\n\r\n\r\n--Makes checkboxes\r\nfunction createCheckbox()\r\n    for i, data in ipairs(ref_buttonData.checkbox) do\r\n        --Sets up reference function\r\n        local buttonNumber = spawnedButtonCount\r\n        local funcName = \"checkbox\"..i\r\n        local func = function() click_checkbox(i, buttonNumber) end\r\n        self.setVar(funcName, func)\r\n        --Sets up label\r\n        local label = \"\"\n        local bc=\"White\"\r\n        if data.state==true then bc=\"Black\" end\r\n        --Creates button and counts it\r\n        self.createButton({\r\n            label=label, click_function=funcName, function_owner=self,\r\n            position=data.pos, height=data.size, width=data.size,\r\n            font_size=data.size, scale=buttonScale,\r\n            color=bc, font_color=buttonFontColor\r\n        })\r\n        spawnedButtonCount = spawnedButtonCount + 1\r\n    end\r\nend\r\n\r\n--Makes counters\r\nfunction createCounter()\r\n    for i, data in ipairs(ref_buttonData.counter) do\r\n        --Sets up display\r\n        local displayNumber = spawnedButtonCount\r\n        --Sets up label\r\n        local label = data.value\r\n        --Sets height/width for display\r\n        local size = data.size\r\n        if data.hideBG == true then size = 0 end\r\n        --Creates button and counts it\r\n        self.createButton({\r\n            label=label, click_function=\"click_none\", function_owner=self,\r\n            position=data.pos, height=size, width=size,\r\n            font_size=data.size, scale=buttonScale,\r\n            color=buttonColor, font_color=buttonFontColor\r\n        })\r\n        spawnedButtonCount = spawnedButtonCount + 1\r\n\r\n        --Sets up add 1\r\n        local funcName = \"counterAdd\"..i\r\n        local func = function() click_counter(i, displayNumber, 1) end\r\n        self.setVar(funcName, func)\r\n        --Sets up label\r\n        local label = \"+\"\r\n        --Sets up position\r\n        local offsetDistance = (data.size/2 + data.size/4) * (buttonScale[1] * 0.002)\r\n        local pos = {data.pos[1] + offsetDistance, data.pos[2], data.pos[3]}\r\n        --Sets up size\r\n        local size = data.size / 2\r\n        --Creates button and counts it\r\n        self.createButton({\r\n            label=label, click_function=funcName, function_owner=self,\r\n            position=pos, height=size, width=size,\r\n            font_size=size, scale=buttonScale,\r\n            color=buttonColor, font_color=buttonFontColor\r\n        })\r\n        spawnedButtonCount = spawnedButtonCount + 1\r\n\r\n        --Sets up subtract 1\r\n        local funcName = \"counterSub\"..i\r\n        local func = function() click_counter(i, displayNumber, -1) end\r\n        self.setVar(funcName, func)\r\n        --Sets up label\r\n        local label = \"-\"\r\n        --Set up position\r\n        local pos = {data.pos[1] - offsetDistance, data.pos[2], data.pos[3]}\r\n        --Creates button and counts it\r\n        self.createButton({\r\n            label=label, click_function=funcName, function_owner=self,\r\n            position=pos, height=size, width=size,\r\n            font_size=size, scale=buttonScale,\r\n            color=buttonColor, font_color=buttonFontColor\r\n        })\r\n        spawnedButtonCount = spawnedButtonCount + 1\r\n    end\r\nend\r\n\r\nfunction createTextbox()\r\n    for i, data in ipairs(ref_buttonData.textbox) do\r\n        --Sets up reference function\r\n        local funcName = \"textbox\"..i\r\n        local func = function(_,_,val,sel) click_textbox(i,val,sel) end\r\n        self.setVar(funcName, func)\r\n\r\n        self.createInput({\r\n            input_function = funcName,\r\n            function_owner = self,\r\n            label          = data.label,\r\n            alignment      = data.alignment,\r\n            position       = data.pos,\r\n            scale          = buttonScale,\r\n            width          = data.width,\r\n            height         = (data.font_size*data.rows)+24,\r\n            font_size      = data.font_size,\r\n            color          = buttonColor,\r\n            font_color     = buttonFontColor,\r\n            value          = data.value,\r\n        })\r\n    end\r\nend",
  "LuaScriptState": "{\"checkbox\":[{\"pos\":[-0.288,0.1,-0.7],\"size\":160,\"state\":false,\"tag\":\"adv1\"},{\"pos\":[-0.2345,0.1,-0.7],\"size\":160,\"state\":false,\"tag\":\"adv1\"},{\"pos\":[-0.181,0.1,-0.7],\"size\":160,\"state\":false,\"tag\":\"adv1\"},{\"pos\":[-0.1275,0.1,-0.7],\"size\":160,\"state\":false,\"tag\":\"adv1\"},{\"pos\":[-0.074,0.1,-0.7],\"size\":160,\"state\":false,\"tag\":\"adv1\"},{\"pos\":[-0.288,0.1,-0.5782],\"size\":160,\"state\":false,\"tag\":\"adv2\"},{\"pos\":[-0.2345,0.1,-0.5782],\"size\":160,\"state\":false,\"tag\":\"adv2\"},{\"pos\":[-0.181,0.1,-0.5782],\"size\":160,\"state\":false,\"tag\":\"adv2\"},{\"pos\":[-0.1275,0.1,-0.5782],\"size\":160,\"state\":false,\"tag\":\"adv2\"},{\"pos\":[-0.074,0.1,-0.5782],\"size\":160,\"state\":false,\"tag\":\"adv2\"},{\"pos\":[-0.288,0.1,-0.4564],\"size\":160,\"state\":false,\"tag\":\"adv3\"},{\"pos\":[-0.2345,0.1,-0.4564],\"size\":160,\"state\":false,\"tag\":\"adv3\"},{\"pos\":[-0.181,0.1,-0.4564],\"size\":160,\"state\":false,\"tag\":\"adv3\"},{\"pos\":[-0.1275,0.1,-0.4564],\"size\":160,\"state\":false,\"tag\":\"adv3\"},{\"pos\":[-0.074,0.1,-0.4564],\"size\":160,\"state\":false,\"tag\":\"adv3\"},{\"pos\":[-0.288,0.1,-0.3346],\"size\":160,\"state\":false,\"tag\":\"adv4\"},{\"pos\":[-0.2345,0.1,-0.3346],\"size\":160,\"state\":false,\"tag\":\"adv4\"},{\"pos\":[-0.181,0.1,-0.3346],\"size\":160,\"state\":false,\"tag\":\"adv4\"},{\"pos\":[-0.1275,0.1,-0.3346],\"size\":160,\"state\":false,\"tag\":\"adv4\"},{\"pos\":[-0.074,0.1,-0.3346],\"size\":160,\"state\":false,\"tag\":\"adv4\"},{\"pos\":[-0.288,0.1,-0.2128],\"size\":160,\"state\":false,\"tag\":\"adv5\"},{\"pos\":[-0.2345,0.1,-0.2128],\"size\":160,\"state\":false,\"tag\":\"adv5\"},{\"pos\":[-0.181,0.1,-0.2128],\"size\":160,\"state\":false,\"tag\":\"adv5\"},{\"pos\":[-0.1275,0.1,-0.2128],\"size\":160,\"state\":false,\"tag\":\"adv5\"},{\"pos\":[-0.074,0.1,-0.2128],\"size\":160,\"state\":false,\"tag\":\"adv5\"},{\"pos\":[-0.288,0.1,-0.091],\"size\":160,\"state\":false,\"tag\":\"adv6\"},{\"pos\":[-0.2345,0.1,-0.091],\"size\":160,\"state\":false,\"tag\":\"adv6\"},{\"pos\":[-0.181,0.1,-0.091],\"size\":160,\"state\":false,\"tag\":\"adv6\"},{\"pos\":[-0.1275,0.1,-0.091],\"size\":160,\"state\":false,\"tag\":\"adv6\"},{\"pos\":[-0.074,0.1,-0.091],\"size\":160,\"state\":false,\"tag\":\"adv6\"},{\"pos\":[-0.288,0.1,0.0308],\"size\":160,\"state\":false,\"tag\":\"adv7\"},{\"pos\":[-0.2345,0.1,0.0308],\"size\":160,\"state\":false,\"tag\":\"adv7\"},{\"pos\":[-0.181,0.1,0.0308],\"size\":160,\"state\":false,\"tag\":\"adv7\"},{\"pos\":[-0.1275,0.1,0.0308],\"size\":160,\"state\":false,\"tag\":\"adv7\"},{\"pos\":[-0.074,0.1,0.0308],\"size\":160,\"state\":false,\"tag\":\"adv7\"},{\"pos\":[-0.288,0.1,0.1526],\"size\":160,\"state\":false,\"tag\":\"adv8\"},{\"pos\":[-0.2345,0.1,0.1526],\"size\":160,\"state\":false,\"tag\":\"adv8\"},{\"pos\":[-0.181,0.1,0.1526],\"size\":160,\"state\":false,\"tag\":\"adv8\"},{\"pos\":[-0.1275,0.1,0.1526],\"size\":160,\"state\":false,\"tag\":\"adv8\"},{\"pos\":[-0.074,0.1,0.1526],\"size\":160,\"state\":false,\"tag\":\"adv8\"},{\"pos\":[-0.288,0.1,0.2744],\"size\":160,\"state\":false,\"tag\":\"adv9\"},{\"pos\":[-0.2345,0.1,0.2744],\"size\":160,\"state\":false,\"tag\":\"adv9\"},{\"pos\":[-0.181,0.1,0.2744],\"size\":160,\"state\":false,\"tag\":\"adv9\"},{\"pos\":[-0.1275,0.1,0.2744],\"size\":160,\"state\":false,\"tag\":\"adv9\"},{\"pos\":[-0.074,0.1,0.2744],\"size\":160,\"state\":false,\"tag\":\"adv9\"},{\"pos\":[-0.288,0.1,0.3962],\"size\":160,\"state\":false,\"tag\":\"adv10\"},{\"pos\":[-0.2345,0.1,0.3962],\"size\":160,\"state\":false,\"tag\":\"adv10\"},{\"pos\":[-0.181,0.1,0.3962],\"size\":160,\"state\":false,\"tag\":\"adv10\"},{\"pos\":[-0.1275,0.1,0.3962],\"size\":160,\"state\":false,\"tag\":\"adv10\"},{\"pos\":[-0.074,0.1,0.3962],\"size\":160,\"state\":false,\"tag\":\"adv10\"},{\"pos\":[-0.288,0.1,0.518],\"size\":160,\"state\":false,\"tag\":\"adv11\"},{\"pos\":[-0.2345,0.1,0.518],\"size\":160,\"state\":false,\"tag\":\"adv11\"},{\"pos\":[-0.181,0.1,0.518],\"size\":160,\"state\":false,\"tag\":\"adv11\"},{\"pos\":[-0.1275,0.1,0.518],\"size\":160,\"state\":false,\"tag\":\"adv11\"},{\"pos\":[-0.074,0.1,0.518],\"size\":160,\"state\":false,\"tag\":\"adv11\"},{\"pos\":[0.642,0.1,-0.81],\"size\":160,\"state\":true,\"tag\":\"potency\"},{\"pos\":[0.6955,0.1,-0.81],\"size\":160,\"state\":false,\"tag\":\"potency\"},{\"pos\":[0.749,0.1,-0.81],\"size\":160,\"state\":false,\"tag\":\"potency\"},{\"pos\":[0.8025,0.1,-0.81],\"size\":160,\"state\":false,\"tag\":\"potency\"},{\"pos\":[0.856,0.1,-0.81],\"size\":160,\"state\":false,\"tag\":\"potency\"},{\"pos\":[0.925,0.1,-0.81],\"size\":160,\"state\":false,\"tag\":\"potency\"},{\"pos\":[0.9785,0.1,-0.81],\"size\":160,\"state\":false,\"tag\":\"potency\"},{\"pos\":[1.032,0.1,-0.81],\"size\":160,\"state\":false,\"tag\":\"potency\"},{\"pos\":[1.0855,0.1,-0.81],\"size\":160,\"state\":false,\"tag\":\"potency\"},{\"pos\":[1.139,0.1,-0.81],\"size\":160,\"state\":false,\"tag\":\"potency\"},{\"pos\":[1.5,0.1,2],\"size\":800,\"state\":false,\"tag\":\"edit\"},{\"pos\":[0,0,0],\"size\":0,\"state\":false,\"tag\":\"dummy\"}],\"counter\":[],\"textbox\":[{\"alignment\":2,\"font_size\":200,\"label\":\"\",\"pos\":[-0.885,0.1,-1.26],\"rows\":16,\"value\":\"\",\"width\":4000},{\"alignment\":2,\"font_size\":200,\"label\":\"\",\"pos\":[0.01,0.1,-1.26],\"rows\":16,\"value\":\"\",\"width\":4000},{\"alignment\":2,\"font_size\":200,\"label\":\"\",\"pos\":[0.9,0.1,-1.26],\"rows\":16,\"value\":\"d\",\"width\":4000},{\"alignment\":3,\"font_size\":200,\"label\":\"Blood Surge\",\"pos\":[0.36,0.1,-0.63],\"rows\":2,\"value\":\"Add 0 die\",\"width\":2800},{\"alignment\":3,\"font_size\":200,\"label\":\"Mend Amount\",\"pos\":[1,0.1,-0.63],\"rows\":2,\"value\":\"\",\"width\":2800},{\"alignment\":3,\"font_size\":200,\"label\":\"Power Bonus\",\"pos\":[0.36,0.1,-0.41],\"rows\":2,\"value\":\"\",\"width\":2800},{\"alignment\":3,\"font_size\":200,\"label\":\"Rouse Re-Roll\",\"pos\":[1,0.1,-0.41],\"rows\":2,\"value\":\"\",\"width\":2800},{\"alignment\":3,\"font_size\":200,\"label\":\"Feeding Penalty\",\"pos\":[0.36,0.1,-0.19],\"rows\":3,\"value\":\"\",\"width\":2800},{\"alignment\":3,\"font_size\":200,\"label\":\"Bane Severity\",\"pos\":[1,0.1,-0.2],\"rows\":2,\"value\":\"\",\"width\":2800},{\"alignment\":2,\"font_size\":300,\"label\":\"\",\"pos\":[-0.8,0.1,-0.7],\"rows\":1,\"value\":\"\",\"width\":4400},{\"alignment\":2,\"font_size\":300,\"label\":\"\",\"pos\":[-0.8,0.1,-0.578],\"rows\":1,\"value\":\"\",\"width\":4400},{\"alignment\":2,\"font_size\":300,\"label\":\"\",\"pos\":[-0.8,0.1,-0.456],\"rows\":1,\"value\":\"\",\"width\":4400},{\"alignment\":2,\"font_size\":300,\"label\":\"\",\"pos\":[-0.8,0.1,-0.334],\"rows\":1,\"value\":\"\",\"width\":4400},{\"alignment\":2,\"font_size\":300,\"label\":\"\",\"pos\":[-0.8,0.1,-0.212],\"rows\":1,\"value\":\"\",\"width\":4400},{\"alignment\":2,\"font_size\":300,\"label\":\"\",\"pos\":[-0.8,0.1,-0.09],\"rows\":1,\"value\":\"\",\"width\":4400},{\"alignment\":2,\"font_size\":300,\"label\":\"\",\"pos\":[-0.8,0.1,0.032],\"rows\":1,\"value\":\"\",\"width\":4400},{\"alignment\":2,\"font_size\":300,\"label\":\"\",\"pos\":[-0.8,0.1,0.154],\"rows\":1,\"value\":\"\",\"width\":4400},{\"alignment\":2,\"font_size\":300,\"label\":\"\",\"pos\":[-0.8,0.1,0.276],\"rows\":1,\"value\":\"\",\"width\":4400},{\"alignment\":2,\"font_size\":300,\"label\":\"\",\"pos\":[-0.8,0.1,0.398],\"rows\":1,\"value\":\"\",\"width\":4400},{\"alignment\":2,\"font_size\":300,\"label\":\"\",\"pos\":[-0.8,0.1,0.52],\"rows\":1,\"value\":\"\",\"width\":4400},{\"alignment\":3,\"font_size\":300,\"label\":\"\",\"pos\":[0.91,0.1,-0.025],\"rows\":1,\"value\":\"\",\"width\":3400},{\"alignment\":3,\"font_size\":300,\"label\":\"\",\"pos\":[0.91,0.1,0.1],\"rows\":1,\"value\":\"\",\"width\":3400},{\"alignment\":2,\"font_size\":300,\"label\":\"\",\"pos\":[0.8,0.1,0.27],\"rows\":1,\"value\":\"\",\"width\":4500},{\"alignment\":2,\"font_size\":300,\"label\":\"\",\"pos\":[0.8,0.1,0.377],\"rows\":1,\"value\":\"\",\"width\":4500},{\"alignment\":2,\"font_size\":300,\"label\":\"\",\"pos\":[0.8,0.1,0.483],\"rows\":1,\"value\":\"\",\"width\":4500},{\"alignment\":2,\"font_size\":300,\"label\":\"\",\"pos\":[0.8,0.1,0.59],\"rows\":1,\"value\":\"\",\"width\":4500},{\"alignment\":2,\"font_size\":200,\"label\":\"\",\"pos\":[0.67,0.1,0.78],\"rows\":2,\"value\":\"\",\"width\":5800},{\"alignment\":2,\"font_size\":200,\"label\":\"\",\"pos\":[0.67,0.1,1],\"rows\":2,\"value\":\"\",\"width\":5800},{\"alignment\":2,\"font_size\":200,\"label\":\"\",\"pos\":[0.67,0.1,1.48],\"rows\":16,\"value\":\"\",\"width\":5800},{\"alignment\":2,\"font_size\":200,\"label\":\"\",\"pos\":[-0.68,0.1,1.25],\"rows\":26,\"value\":\"d\",\"width\":5800}]}",
  "XmlUI": ""
}